llm_engines/__init__.py
llm_engines/claude.py
llm_engines/cli.py
llm_engines/deepseek.py
llm_engines/fireworks.py
llm_engines/gemini.py
llm_engines/grok.py
llm_engines/mistral.py
llm_engines/openai_text.py
llm_engines/sglang.py
llm_engines/together.py
llm_engines/utils.py
llm_engines/vllm.py
llm_engines/cache/__init__.py
llm_engines/cache/cache_dict.py
llm_engines/cache/cache_lru.py
llm_engines/cache/cache_sqlite3.py
llm_engines/cache/cache_utils.py
llm_engines-0.0.25.dist-info/licenses/LICENSE
llm_engines-0.0.25.dist-info/METADATA
llm_engines-0.0.25.dist-info/WHEEL
llm_engines-0.0.25.dist-info/entry_points.txt
llm_engines-0.0.25.dist-info/top_level.txt
llm_engines-0.0.25.dist-info/RECORD
