Metadata-Version: 2.4
Name: llm-engines
Version: 0.0.25
Summary: A unified inference engine for large language models (LLMs) including open-source models (VLLM, SGLang, Together) and commercial models (OpenAI, Mistral, Claude).
Home-page: https://github.com/jdf-prog/LLM-Engines
Author: Dongfu Jiang
Author-email: dongfu.jiang@uwaterloo.ca
License-File: LICENSE
Requires-Dist: fire
Requires-Dist: openai
Requires-Dist: google-generativeai
Requires-Dist: accelerate
Requires-Dist: transformers
Requires-Dist: torch
Requires-Dist: Pillow
Requires-Dist: torch
Requires-Dist: tqdm
Requires-Dist: numpy
Requires-Dist: requests
Requires-Dist: sentencepiece
Requires-Dist: vllm
Requires-Dist: together
Requires-Dist: icecream
Requires-Dist: prettytable
Requires-Dist: mistralai
Requires-Dist: anthropic
Requires-Dist: fastapi
Requires-Dist: fireworks-ai
Provides-Extra: flash-attn
Requires-Dist: flash-attn; extra == "flash-attn"
Provides-Extra: sglang
Requires-Dist: sglang[all]; extra == "sglang"
Dynamic: author
Dynamic: author-email
Dynamic: description
Dynamic: description-content-type
Dynamic: home-page
Dynamic: license-file
Dynamic: provides-extra
Dynamic: requires-dist
Dynamic: summary
